fondat/redis.py
fondat_redis-4.0.0.dist-info/LICENSE
fondat_redis-4.0.0.dist-info/WHEEL
fondat_redis-4.0.0.dist-info/METADATA
fondat_redis-4.0.0.dist-info/RECORD
