Metadata-Version: 2.1
Name: fondat-redis
Version: 4.0.0
Summary: Fondat module for Redis.
Home-page: https://github.com/fondat/fondat-redis/
License: MIT
Keywords: asgi,framework,resource,openapi
Author: fondat-redis authors
Requires-Python: >=3.10,<4.0
Classifier: Development Status :: 5 - Production/Stable
Classifier: Intended Audience :: Developers
Classifier: License :: OSI Approved :: MIT License
Classifier: Programming Language :: Python :: 3
Classifier: Programming Language :: Python :: 3.10
Classifier: Topic :: Software Development :: Libraries :: Application Frameworks
Requires-Dist: fondat (>=4.0.0,<5.0.0)
Requires-Dist: redis (>=4.3,<5.0)
Project-URL: Documentation, https://github.com/fondat/fondat-redis/wiki
